pyburstlib/__init__.py
pyburstlib/client.py
pyburstlib/config.py
pyburstlib/constants.py
pyburstlib/exceptions.py
pyburstlib/log.py
pyburstlib/lib/__init__.py
pyburstlib/lib/brs_address.py
pyburstlib/lib/crypto.py
pyburstlib/lib/utils/__init__.py
pyburstlib/lib/utils/converters.py
pyburstlib/wallet_api/__init__.py
pyburstlib/wallet_api/accounts.py
pyburstlib/wallet_api/base.py
pyburstlib/wallet_api/server.py
pyburstlib/wallet_api/models/__init__.py
pyburstlib/wallet_api/models/accounts.py
pyburstlib/wallet_api/models/base.py
pyburstlib/wallet_api/models/server.py
pyburstlib-1.1.0.dev0.dist-info/METADATA
pyburstlib-1.1.0.dev0.dist-info/RECORD
pyburstlib-1.1.0.dev0.dist-info/WHEEL
pyburstlib-1.1.0.dev0.dist-info/top_level.txt
