Metadata-Version: 2.1
Name: pyburstlib
Version: 1.1.0.dev0
Summary: A python library for working with Burstcoin
Home-page: https://github.com/beatsbears/pyburstlib
Author: drownedcoast
License: MIT License
Keywords: burst burstcoin pocc
Platform: UNKNOWN
Requires-Python: >=3.3
Requires-Dist: attrs (==17.4.0)
Requires-Dist: certifi (==2018.1.18)
Requires-Dist: cffi (==1.11.5)
Requires-Dist: chardet (==3.0.4)
Requires-Dist: idna (==2.6)
Requires-Dist: pluggy (==0.6.0)
Requires-Dist: py (==1.5.2)
Requires-Dist: pycparser (==2.18)
Requires-Dist: PyNaCl (==1.2.1)
Requires-Dist: pytest (==3.4.2)
Requires-Dist: requests (==2.18.4)
Requires-Dist: six (==1.11.0)
Requires-Dist: urllib3 (==1.22)
